cardgame/__init__.py
cardgame/base.py
cardgame/decks.py
cardgame/tools.py
samples/battle.py
samples/solitary.py
naturalcardgame-0.1.3.dist-info/METADATA
naturalcardgame-0.1.3.dist-info/WHEEL
naturalcardgame-0.1.3.dist-info/licenses/LICENSE
naturalcardgame-0.1.3.dist-info/RECORD
